CHANGES.rst
CONTRIBUTORS.rst
DEVELOP.rst
LICENSE.GPL
LICENSE.rst
MANIFEST.in
README.rst
setup.cfg
setup.py
docs/conf.py
docs/index.rst
src/collective/__init__.py
src/collective.easyformplugin.filemailer.egg-info/PKG-INFO
src/collective.easyformplugin.filemailer.egg-info/SOURCES.txt
src/collective.easyformplugin.filemailer.egg-info/dependency_links.txt
src/collective.easyformplugin.filemailer.egg-info/entry_points.txt
src/collective.easyformplugin.filemailer.egg-info/namespace_packages.txt
src/collective.easyformplugin.filemailer.egg-info/not-zip-safe
src/collective.easyformplugin.filemailer.egg-info/requires.txt
src/collective.easyformplugin.filemailer.egg-info/top_level.txt
src/collective/easyformplugin/__init__.py
src/collective/easyformplugin/filemailer/__init__.py
src/collective/easyformplugin/filemailer/configure.zcml
src/collective/easyformplugin/filemailer/interfaces.py
src/collective/easyformplugin/filemailer/mailer.py
src/collective/easyformplugin/filemailer/setuphandlers.py
src/collective/easyformplugin/filemailer/testing.py
src/collective/easyformplugin/filemailer/vocabularies.py
src/collective/easyformplugin/filemailer/vocabularies.zcml
src/collective/easyformplugin/filemailer/locales/README.rst
src/collective/easyformplugin/filemailer/locales/__init__.py
src/collective/easyformplugin/filemailer/locales/collective.easyformplugin.filemailer.pot
src/collective/easyformplugin/filemailer/locales/update.py
src/collective/easyformplugin/filemailer/locales/update.sh
src/collective/easyformplugin/filemailer/locales/en/LC_MESSAGES/collective.easyformplugin.filemailer.po
src/collective/easyformplugin/filemailer/locales/nl/LC_MESSAGES/collective.easyformplugin.filemailer.po
src/collective/easyformplugin/filemailer/profiles/default/browserlayer.xml
src/collective/easyformplugin/filemailer/profiles/default/metadata.xml
src/collective/easyformplugin/filemailer/profiles/default/registry/main.xml
src/collective/easyformplugin/filemailer/profiles/uninstall/browserlayer.xml
src/collective/easyformplugin/filemailer/tests/__init__.py
src/collective/easyformplugin/filemailer/tests/test_robot.py
src/collective/easyformplugin/filemailer/tests/test_setup.py
src/collective/easyformplugin/filemailer/tests/robot/test_example.robot